{
  "metadata": {
    "lastUpdated": "2026-05-12T19:26:35.650Z",
    "version": "5.0",
    "totalEvents": 24,
    "sourcesChecked": 250,
    "sourcesWorking": 250,
    "errors": [],
    "updateMethod": "COMPREHENSIVE_MULTI_SOURCE",
    "translationQuality": "ADVANCED_GRAMMAR",
    "language": "ru",
    "stats": {
      "raw": 250,
      "processed": 24,
      "final": 24,
      "byType": {
        "murder": 7,
        "other": 10,
        "attack": 4,
        "discrimination": 1,
        "arrest": 2
      },
      "byCountry": {
        "Nigeria": 8,
        "Pakistan": 1,
        "India": 2,
        "Saudi Arabia": 1,
        "Mozambique": 1,
        "Somalia": 1,
        "Democratic Republic of the Congo": 1,
        "Iran": 3,
        "China": 2,
        "Colombia": 1,
        "Central African Republic": 2,
        "Philippines": 1
      }
    },
    "generatedAt": "12.05.2026, 19:26:35",
    "archivedTotal": 500,
    "archiveUpdated": "2026-05-12T19:26:35.723Z"
  },
  "events": [
    {
      "date": "2026-05-11",
      "lat": 9.0029,
      "lng": 9.5805,
      "country": "Nigeria",
      "city": "Plateau",
      "type": "murder",
      "title": "128,750 христиане в Nigeria убит 17 годы: $10 million cover-up геноцид в Nigeria",
      "description": "Tinubu’s administration has launched $10 million lobbying front silence human rights accountability в U.S. и whitewash геноцид Nigerian христиане. This isn’t just spin — it’s calculated усилие rewrite history пока innocent",
      "source": "zenit",
      "url": "https://zenit.org/2026/05/11/128750-christians-in-nigeria-killed-over-17-years-the-10-million-cover-up-of-the-genocide-in-nigeria/",
      "victims": 750
    },
    {
      "date": "2026-05-05",
      "lat": 6.5999,
      "lng": 3.3024,
      "country": "Nigeria",
      "city": "Lagos",
      "type": "murder",
      "title": "12 христиане убит в Nigeria",
      "description": "Террористы из Исламское государство West Africa провинция (ISWAP) убит least 12 люди и сожжён церковь building в атака на христианин деревня в northeastern Nigeria’s Adamawa штат, according international христианин aid organizati",
      "source": "christiantoday",
      "url": "https://www.christiantoday.com/news/12-christians-killed-in-nigeria",
      "victims": 12
    },
    {
      "date": "2026-05-05",
      "lat": 6.6368,
      "lng": 3.2386,
      "country": "Nigeria",
      "city": "Lagos",
      "type": "murder",
      "title": "Exclusive из Nigeria: христианская семья сожжён Alive",
      "description": "Thousands христиане have been убит, leaving 400 widows struggling для survival после being перемещён фулани исламский экстремисты. Photo Antonio Graceffo. Driving из Nigeria’s столица город Abuja toward Jos, one enters kill zone",
      "source": "newsapi:Freerepublic.com",
      "url": "https://freerepublic.com/focus/f-religion/4377685/posts",
      "victims": 0
    },
    {
      "date": "2026-05-11",
      "lat": 24.9284,
      "lng": 66.844,
      "country": "Pakistan",
      "city": "Karachi",
      "type": "murder",
      "title": "Христианин Dies Doing вынужден Labor в Pakistan",
      "description": "Around 5.m. на май 7, Shabbir Masih, 33-год-old христианин sanitation worker в Pakistan, погиб после inhaling toxic gases пока doing dangerous job his руководители вынужден him do. Masih погиб working inside 25-foot-deep mainline sewer operat",
      "source": "persecution",
      "url": "https://persecution.org/2026/05/11/christian-man-dies-doing-forced-labor-in-pakistan/",
      "victims": 0
    },
    {
      "date": "2026-05-11",
      "lat": 21.4936,
      "lng": 81.9523,
      "country": "India",
      "city": "Chhattisgarh",
      "type": "other",
      "title": "Люди’s трибунал Claims Odisha правительство Complicit в христианин гонение",
      "description": "Люди’s трибунал, led prominent civil rights activists в India, submitted letter на прошлой неделе Odisha правительство accusing штат administration being complicit в гонение христиане. letter called out conduct t",
      "source": "persecution",
      "url": "https://persecution.org/2026/05/11/peoples-tribunal-claims-odisha-government-complicit-in-christian-persecution/",
      "victims": 0
    },
    {
      "date": "2026-05-06",
      "lat": 10.3305,
      "lng": 7.4175,
      "country": "Nigeria",
      "city": "Kaduna",
      "type": "other",
      "title": "Христиане must defend themselves amid rising гонение, Nigerian prelate says",
      "description": "Following resurgence violence в Nigeria, judicial vicar порт Harcourt Diocese has called для христиане promote peace пока not ignoring need protect their lives.",
      "source": "newsapi:Ewtnnews.com",
      "url": "https://www.ewtnnews.com/world/africa/christians-must-defend-themselves-amid-rising-persecution-nigerian-prelate-says",
      "victims": 0
    },
    {
      "date": "2026-05-11",
      "lat": 24.541,
      "lng": 46.8521,
      "country": "Saudi Arabia",
      "city": "Riyadh",
      "type": "attack",
      "title": "Growing Up христианин в Churchless Kingdom Saudi Arabia",
      "description": "Атаки на церкви are harsh reality в many countries. But Saudi Arabia is not one them. birthplace both ислам и Wahhabi radicalism, this country more than 35 million люди has more than handful who would be up для task. B",
      "source": "persecution",
      "url": "https://persecution.org/2026/05/11/growing-up-christian-in-the-churchless-kingdom-of-saudi-arabia/",
      "victims": 0
    },
    {
      "date": "2026-05-07",
      "lat": 10.5907,
      "lng": 7.2635,
      "country": "Nigeria",
      "city": "Kaduna",
      "type": "discrimination",
      "title": "Joe Lonsdale: религиозный гонение в Nigeria is critical global issue, Iran’s destabilizing influence на Lebanon, и US is poised для nuclear energy resurgence | Shawn Ryan Show",
      "description": "Религиозный tensions в Nigeria highlight global impact экстремист groups и geopolitical instability. post Joe Lonsdale: религиозный гонение в Nigeria is critical global issue, Iran’s destabilizing influence на Lebanon, и US is p",
      "source": "newsapi:Crypto Briefing",
      "url": "https://cryptobriefing.com/joe-lonsdale-religious-persecution-in-nigeria-is-a-critical-global-issue-irans-destabilizing-influence-on-lebanon-and-the-us-is-poised-for-a-nuclear-energy-resurgence-shawn-ryan-show/",
      "victims": 0
    },
    {
      "date": "2026-05-08",
      "lat": 11.796,
      "lng": 8.8042,
      "country": "Nigeria",
      "city": "Kano",
      "type": "other",
      "title": "ICC Releases Report Exposing Nigeria’s $10 Million геноцид Cover-Up",
      "description": "New report из International христианин Concern (ICC) highlights how Nigeria’s правительство is weaponizing misinformation hide десятилетия-long кампания violence against христиане. Written ICC Fellow Justin Joseph, “Nigeria’s $10 Million Geno",
      "source": "persecution",
      "url": "https://persecution.org/2026/05/08/icc-releases-report-exposing-nigerias-10-million-genocide-cover-up/",
      "victims": 190
    },
    {
      "date": "2026-05-08",
      "lat": -12.1116,
      "lng": 40.7452,
      "country": "Mozambique",
      "city": "Cabo Delgado",
      "type": "attack",
      "title": "Historic Mozambique церковь разрушен в экстремист атака as церковь leaders appeal для peace",
      "description": "Церковь leaders в northern Mozambique have renewed calls для peace и религиозный unity после боевики разрушен historic церковь во время violent рейд в Cabo Delgado провинция.",
      "source": "christiantoday",
      "url": "https://www.christiantoday.com/news/historic-mozambique-church-destroyed-in-extremist-attack-as-church-leaders-appeal-for-peace",
      "victims": 0
    },
    {
      "date": "2026-05-05",
      "lat": 2.1479,
      "lng": 45.1037,
      "country": "Somalia",
      "city": "Mogadishu",
      "type": "murder",
      "title": "Community Grieves Teenage христианин’s смерть",
      "description": "Смерть христианин подросток has left void в Mwingi, Kenya. во время recent вечер в Nguni area, Somali боевики moving through grazing routes along local farmland застрелен 14-год-old James Mutemi, убийство him. Another local escaped с inj",
      "source": "persecution",
      "url": "https://persecution.org/2026/05/05/community-grieves-teenage-christians-death/",
      "victims": 0
    },
    {
      "date": "2026-05-07",
      "lat": -4.5929,
      "lng": 15.1234,
      "country": "Democratic Republic of the Congo",
      "city": "Kinshasa",
      "type": "murder",
      "title": "ADF атаки Several деревни в Eastern DRC",
      "description": "После brief calm, христиане who had fled и resettled в Eastern DRC faced renewed ADF нападения. на май 5, ADF атаки occurred Katerrain и Mangambo, деревни situated along borders North Kivu и Ituri провинции, resulting в leas",
      "source": "persecution",
      "url": "https://persecution.org/2026/05/07/adf-attacks-several-villages-in-eastern-drc/",
      "victims": 24
    },
    {
      "date": "2026-04-30",
      "lat": 9.3326,
      "lng": 9.6411,
      "country": "Nigeria",
      "city": "Plateau",
      "type": "other",
      "title": "Nigeria faces stricter US aid terms ‘религиозный гонение’",
      "description": "US House комитет has advanced bill с stricter conditions на US aid Nigeria, citing concerns security и alleged религиозный гонение. Read More: https://punchng.com/nigeria-faces-stricter-us-aid-terms--религиозный-гонение/",
      "source": "newsapi:The Punch",
      "url": "https://punchng.com/nigeria-faces-stricter-us-aid-terms-over-religious-persecution/",
      "victims": 0
    },
    {
      "date": "2026-05-08",
      "lat": 28.5264,
      "lng": 76.919,
      "country": "India",
      "city": "Delhi",
      "type": "attack",
      "title": "Христиане decry гонение в India's heartland",
      "description": "С христиане в India increasingly targeted индус дружинники, жертвы say полиция often side с their attackers.",
      "source": "newsapi:DW (English)",
      "url": "https://www.dw.com/en/christians-decry-persecution-in-indias-heartland/a-77095929",
      "victims": 0
    },
    {
      "date": "2026-05-11",
      "lat": 32.6387,
      "lng": 51.4652,
      "country": "Iran",
      "city": "Isfahan",
      "type": "other",
      "title": "Donald Trump acknowledges limits Jacksonism, Thierry Meyssan",
      "description": "Events are going badly. time когда президент Trump is launching his Kuturkampf against католическая церковь reaffirm Anglo-Saxon и not Aztec character his country, he is страдания heavy failure against Iran. He must note that his way",
      "source": "newsapi:Red Voltaire",
      "url": "https://www.voltairenet.org/article224467.html",
      "victims": 0
    },
    {
      "date": "2026-05-10",
      "lat": 32.823,
      "lng": 51.8454,
      "country": "Iran",
      "city": "Isfahan",
      "type": "other",
      "title": "Trump Promotes Claim He Has 'Better Understanding' Библия Than папа Leo",
      "description": "Trump shared clip controversial пастор declaring that папа is \"sincerely wrong когда it comes Iran\" just дни после Marco Rubio's Vatican meeting.",
      "source": "newsapi:HuffPost",
      "url": "https://www.huffpost.com/entry/baptist-pastor-robert-jeffress-trump-pope-better-understanding-bible_n_6a006d50e4b0cb033e521809",
      "victims": 0
    },
    {
      "date": "2026-05-07",
      "lat": 12.1582,
      "lng": 8.7073,
      "country": "Nigeria",
      "city": "Kano",
      "type": "murder",
      "title": "US lawmaker urges Trump take ‘forceful action’ плато атака",
      "description": "US lawmaker is urging Trump administration take forceful action protect христиане following deadly плато атака на mourners в Nigeria. Read More: https://punchng.com/us-lawmaker-urges-trump--take-forceful-action--плато-atta",
      "source": "newsapi:The Punch",
      "url": "https://punchng.com/us-lawmaker-urges-trump-to-take-forceful-action-over-plateau-attack/",
      "victims": 0
    },
    {
      "date": "2026-05-11",
      "lat": 31.2906,
      "lng": 121.5702,
      "country": "China",
      "city": "Shanghai",
      "type": "arrest",
      "title": "Семьи Americans заключён в China have ‘glimmer hope’ that Trump can free loved ones во время Xi meeting",
      "description": "\"This президент has just remarkable way doing things that most люди say are impossible,\" daughter заключён христианин пастор told Post.",
      "source": "newsapi:New York Post",
      "url": "https://nypost.com/2026/05/11/us-news/family-of-pastor-ezra-jin-dawn-hunt-ask-trump-to-free-them-from-china/",
      "victims": 0
    },
    {
      "date": "2026-05-08",
      "lat": 4.7374,
      "lng": -74.0753,
      "country": "Colombia",
      "city": "Bogota",
      "type": "other",
      "title": "Христиане petition для protection пасторы в Colombia following убийства",
      "description": "Petition will be presented new президент.",
      "source": "christiantoday",
      "url": "https://www.christiantoday.com/news/christians-petition-for-protection-of-pastors-in-colombia-following-murders",
      "victims": 0
    },
    {
      "date": "2026-05-11",
      "lat": 36.4803,
      "lng": 59.6338,
      "country": "Iran",
      "city": "Mashhad",
      "type": "attack",
      "title": "US-Israel War атаки Ancient христианин Heritage",
      "description": "It does not take ракета scientist figure out that US-Israel’s conflicts are widespread и continuous throughout Middle East as they have сейчас initiated unprovoked атака against Iran. read this article в following languages, clic",
      "source": "newsapi:Globalresearch.ca",
      "url": "https://www.globalresearch.ca/us-israel-war-attacks-ancient-christian-heritage/5925831",
      "victims": 0
    },
    {
      "date": "2026-05-11",
      "lat": 4.2512,
      "lng": 18.6083,
      "country": "Central African Republic",
      "city": "Bangui",
      "type": "other",
      "title": "Папа warns main угроза common религия и science is отказ objective truth",
      "description": "Папа Leo XIV pointed out that both science и церковь clearly teach that caring для planet is угрожали irresponsible exploitation both люди и natural world.",
      "source": "catholicNewsAgency",
      "url": "https://www.ewtnnews.com/vatican/pope-warns-main-threat-common-to-religion-and-science-is-denial-of-objective-truth",
      "victims": 0
    },
    {
      "date": "2026-05-11",
      "lat": 43.5805,
      "lng": 87.4413,
      "country": "China",
      "city": "Xinjiang",
      "type": "arrest",
      "title": "Trump vows discuss freedom Jimmy Lai, христианские лидеры задержан в China",
      "description": "Президент likened call free Lai complexity releasing indicted former FBI Director James Comey as семьи Chinese prisoners rallied outside White House.",
      "source": "catholicNewsAgency",
      "url": "https://www.ewtnnews.com/world/us/trump-vows-to-discuss-freedom-of-jimmy-lai-christian-leaders-detained-in-china",
      "victims": 0
    },
    {
      "date": "2026-05-11",
      "lat": 14.6367,
      "lng": 120.7644,
      "country": "Philippines",
      "city": "Manila",
      "type": "other",
      "title": "В new signature drive, Filipino церковь breaks bonds политический dynasties",
      "description": "New церковь-backed signature drive aims end политический dynasties в Philippines, which have controlled local правительства и worsened poverty для век.",
      "source": "crux",
      "url": "https://cruxnow.com/church-in-asia/2026/05/in-new-signature-drive-filipino-church-breaks-bonds-of-political-dynasties/",
      "victims": 0
    },
    {
      "date": "2026-05-10",
      "lat": 4.3061,
      "lng": 18.413,
      "country": "Central African Republic",
      "city": "Bangui",
      "type": "other",
      "title": "Кардинал: Leo XIV is unifier, but will surprise us",
      "description": "“reliable и constant” мужчина who speaks “without guile” и will be able embody unifying figure в католическая церковь through his “audacious wisdom”: this is how кардинал Jean-Paul Vesco describes папа Leo XIV. One год после participating в",
      "source": "aleteia",
      "url": "https://aleteia.org/2026/05/10/cardinal-leo-xiv-is-a-unifier-but-will-surprise-us/",
      "victims": 0
    }
  ]
}