{
  "metadata": {
    "lastUpdated": "2026-07-08T19:02:33.580Z",
    "version": "5.0",
    "totalEvents": 45,
    "sourcesChecked": 1297,
    "sourcesWorking": 1297,
    "errors": [],
    "updateMethod": "COMPREHENSIVE_MULTI_SOURCE",
    "translationQuality": "ADVANCED_GRAMMAR",
    "language": "ru",
    "stats": {
      "raw": 1297,
      "processed": 45,
      "final": 45,
      "byType": {
        "murder": 12,
        "kidnapping": 5,
        "arrest": 6,
        "other": 17,
        "discrimination": 3,
        "attack": 2
      },
      "byCountry": {
        "Nigeria": 11,
        "Pakistan": 6,
        "India": 7,
        "Iran": 3,
        "China": 6,
        "Iraq": 2,
        "Indonesia": 2,
        "Kenya": 1,
        "Central African Republic": 2,
        "Venezuela": 2,
        "Sudan": 1,
        "Mexico": 1,
        "Colombia": 1
      }
    },
    "generatedAt": "08.07.2026, 19:02:33",
    "archivedTotal": 500,
    "archiveUpdated": "2026-07-08T19:02:33.652Z"
  },
  "events": [
    {
      "date": "2026-06-30",
      "lat": 12.1268,
      "lng": 8.7664,
      "country": "Nigeria",
      "city": "Kano",
      "type": "murder",
      "title": "Two христиане убит, Seven похищен в Kaduna штат, Nigeria",
      "description": "ABUJA, Nigeria (христианин Daily International–утро Star News) – Suspected пастухи фулани на четверг (июнь 25) raided two христианин деревни в same area Kaduna штат, Nigeria, убийство two христиане, похищение seven others и injuring d",
      "source": "morningstarnews",
      "url": "https://morningstarnews.org/2026/06/two-christians-slain-seven-kidnapped-in-kaduna-state-nigeria/",
      "victims": 24
    },
    {
      "date": "2026-06-27",
      "lat": 10.5899,
      "lng": 7.2035,
      "country": "Nigeria",
      "city": "Kaduna",
      "type": "murder",
      "title": "Фулани террористы kill 28 христиане в central Nigeria",
      "description": "Пастухи фулани guided toward христианские лидеры на понедельник убит 28 христиане, including пастор, в рейд на деревня в плато штат, Nigeria, sources said.",
      "source": "christiantoday",
      "url": "https://www.christiantoday.com/news/fulani-terrorists-kill-28-christians-in-central-nigeria",
      "victims": 28
    },
    {
      "date": "2026-06-30",
      "lat": 33.9411,
      "lng": 71.6301,
      "country": "Pakistan",
      "city": "Peshawar",
      "type": "kidnapping",
      "title": "Exam Ordered для похищен христианин Girl в Pakistan",
      "description": "LAHORE, Pakistan (христианин Daily International–утро Star News) – суд в Pakistan has ordered medical examination determine век христианин girl похищен, forcibly converted ислам и married мусульманин, sources said. Amber Nad",
      "source": "morningstarnews",
      "url": "https://morningstarnews.org/2026/06/exam-ordered-for-kidnapped-christian-girl-in-pakistan/",
      "victims": 0
    },
    {
      "date": "2026-07-02",
      "lat": 26.9004,
      "lng": 80.8045,
      "country": "India",
      "city": "Uttar Pradesh",
      "type": "arrest",
      "title": "Пастор в India Faces False обвинение, сожжён церковь Building",
      "description": "NEW DELHI (христианин Daily International–утро Star News) – wife пастор falsely named в criminal case в India на этой неделе sought арест сикх мужчина suspected setting their церковь building и residence ablaze на июнь 14, sources",
      "source": "morningstarnews",
      "url": "https://morningstarnews.org/2026/07/pastor-in-india-faces-false-charge-burned-church-building/",
      "victims": 0
    },
    {
      "date": "2026-07-06",
      "lat": 9.1865,
      "lng": 7.3782,
      "country": "Nigeria",
      "city": "Abuja",
      "type": "murder",
      "title": "Nearly 30,000 христиане убит в Nigeria в six годы",
      "description": "Tens thousands христиане are losing their lives violence в Nigeria, many them hands radicalised пастухи фулани, new report has warned.",
      "source": "christiantoday",
      "url": "https://www.christiantoday.com/news/nearly-30-000-christians-killed-in-nigeria-in-six-years",
      "victims": 0
    },
    {
      "date": "2026-07-07",
      "lat": 32.8018,
      "lng": 51.5415,
      "country": "Iran",
      "city": "Isfahan",
      "type": "other",
      "title": "Iran threatens seize one последний remaining протестантские церкви в Tehran",
      "description": "One последний remaining historic протестантские церкви в Iran is reportedly facing угроза конфискация Iranian правительство, drawing renewed international attention country's treatment религиозный minorities.",
      "source": "christiantoday",
      "url": "https://www.christiantoday.com/news/iran-threatens-to-seize-one-of-last-remaining-protestant-churches-in-tehran",
      "victims": 0
    },
    {
      "date": "2026-07-07",
      "lat": 32.633,
      "lng": 51.4178,
      "country": "Iran",
      "city": "Isfahan",
      "type": "other",
      "title": "Iran threatens seize one последний remaining протестантские церкви в Tehran",
      "description": "One последний remaining historic протестантские церкви в Iran is reportedly facing угроза конфискация Iranian правительство, drawing renewed international attention country's treatment религиозный minorities.",
      "source": "newsapi:The Christian Post",
      "url": "https://www.christianpost.com/news/iranian-regime-threatens-to-seize-protestant-church-report.html",
      "victims": 0
    },
    {
      "date": "2026-06-16",
      "lat": 11.8787,
      "lng": 8.7153,
      "country": "Nigeria",
      "city": "Kano",
      "type": "kidnapping",
      "title": "‘Eight годы is too long’: христианин advocacy groups rally для похищен Nigerian schoolgirl's freedom",
      "description": "Христианин Nigerian schoolgirl Leah Sharibu was похищен eight годы ago исламский экстремисты. Unlike most classmates she was похищен с, she has never been freed.",
      "source": "christiantoday",
      "url": "https://www.christiantoday.com/news/eight-years-is-too-long-christian-advocacy-groups-rally-for-abducted-nigerian-schoolgirl-s-freedom",
      "victims": 0
    },
    {
      "date": "2026-07-05",
      "lat": 39.6803,
      "lng": 116.1598,
      "country": "China",
      "city": "Beijing",
      "type": "arrest",
      "title": "Chinese пастор Arrives в U.S. после 8 месяцы в тюрьма",
      "description": "Chinese власти недавно released Zion церковь пастор ‌Ezra Jin, who had been задержан в southern China для past eight месяцы. Jin arrived в Los Angeles, California, на суббота и was welcomed ChinaAid. власти арестован Jin и 17 o",
      "source": "persecution",
      "url": "https://persecution.org/2026/07/05/chinese-pastor-arrives-in-u-s-after-8-months-in-prison/",
      "victims": 0
    },
    {
      "date": "2026-07-02",
      "lat": 36.1898,
      "lng": 43.241,
      "country": "Iraq",
      "city": "Mosul",
      "type": "other",
      "title": "Coalition Asks U.S. Intervene в Case Syrian христианин",
      "description": "Advocacy groups недавно wrote Thomas Barrack, U.S. посол Republic Türkiye и Envoy Syria и Iraq, asking U.S. intervene в задержание Syrian христианин. letter, sent на июнь 25, was penned в Defense Chris",
      "source": "persecution",
      "url": "https://persecution.org/2026/07/02/coalition-asks-u-s-to-intervene-in-case-of-syrian-christian/",
      "victims": 0
    },
    {
      "date": "2026-06-30",
      "lat": -6.3627,
      "lng": 106.8377,
      "country": "Indonesia",
      "city": "Jakarta",
      "type": "discrimination",
      "title": "Мусульмане Reject христианин молитва House в Indonesia",
      "description": "На июнь 24, group мусульмане атакован молитва house в Hegarmanah Indah Housing Complex в West Java, Indonesia, demanding that it be закрыт. violent толпа атакован several members церковь behind молитва house и угрожали bu",
      "source": "persecution",
      "url": "https://persecution.org/2026/06/30/muslims-reject-christian-prayer-house-in-indonesia/",
      "victims": 0
    },
    {
      "date": "2026-06-23",
      "lat": 10.5375,
      "lng": 7.2568,
      "country": "Nigeria",
      "city": "Kaduna",
      "type": "murder",
      "title": "Первый memorial христиане убит в Nigeria unveiled",
      "description": "Every год thousands are убит в Nigeria.",
      "source": "christiantoday",
      "url": "https://www.christiantoday.com/news/first-memorial-to-christians-killed-in-nigeria-unveiled",
      "victims": 0
    },
    {
      "date": "2026-06-19",
      "lat": 26.8773,
      "lng": 80.8466,
      "country": "India",
      "city": "Uttar Pradesh",
      "type": "discrimination",
      "title": "Indian христиане атакован в церковь толпа",
      "description": "Chhattisgarh has allegedly запрещён домашние церкви promote \"cultural harmony\".",
      "source": "christiantoday",
      "url": "https://www.christiantoday.com/news/indian-christians-attacked-in-church-by-mob",
      "victims": 0
    },
    {
      "date": "2026-07-06",
      "lat": 33.9093,
      "lng": 72.9944,
      "country": "Pakistan",
      "city": "Islamabad",
      "type": "arrest",
      "title": "Христианин в Pakistan Acquitted богохульство обвинение",
      "description": "LAHORE, Pakistan (христианин Daily International–утро Star News) – суд в Pakistan на понедельник (июль 6) acquitted Catholic accused богохульство, his lawyer said. Attorney Asad Jamal Lahore High суд said Lahore Additional Sessions судья",
      "source": "morningstarnews",
      "url": "https://morningstarnews.org/2026/07/christian-in-pakistan-acquitted-of-blasphemy-charge/",
      "victims": 0
    },
    {
      "date": "2026-07-06",
      "lat": 10.2951,
      "lng": 7.2833,
      "country": "Nigeria",
      "city": "Kaduna",
      "type": "kidnapping",
      "title": "Христианин Campus Group Leaders в Nigeria Remain пропавший без вести",
      "description": "ABUJA, Nigeria (христианин Daily International–утро Star News) – Three недели после похищение Scripture Union Nigeria’s national general director в southeast Nigeria, he и seven other fellowship leaders remain пропавший без вести, according report",
      "source": "morningstarnews",
      "url": "https://morningstarnews.org/2026/07/christian-campus-group-leaders-in-nigeria-remain-missing/",
      "victims": 0
    },
    {
      "date": "2026-06-26",
      "lat": -1.2328,
      "lng": 36.5984,
      "country": "Kenya",
      "city": "Nairobi",
      "type": "attack",
      "title": "Христианин атакован для Evangelistic Outreach в Uganda",
      "description": "NAIROBI, Kenya (утро Star News) – христианин атакован после he и his wife participated в evangelistic outreach в eastern Uganda на июнь 14 is still receiving medical treatment для his ранения, sources said. David Musobya, 37, had traveled",
      "source": "morningstarnews",
      "url": "https://morningstarnews.org/2026/06/christian-attacked-for-evangelistic-outreach-in-uganda/",
      "victims": 0
    },
    {
      "date": "2026-07-07",
      "lat": 33.9122,
      "lng": 73.0966,
      "country": "Pakistan",
      "city": "Islamabad",
      "type": "other",
      "title": "Tensions Inflamed богохульство Accusation в Pakistan",
      "description": "LAHORE, Pakistan (христианин Daily International–утро Star News) – More than two dozen христианские семьи were вынужден flee their homes в Pakistan на прошлой неделе после allegations богохульство against пастор living в United штаты triggered fe",
      "source": "morningstarnews",
      "url": "https://morningstarnews.org/2026/07/tensions-inflamed-by-blasphemy-accusation-in-pakistan/",
      "victims": 0
    },
    {
      "date": "2026-07-07",
      "lat": 9.3465,
      "lng": 9.3539,
      "country": "Nigeria",
      "city": "Plateau",
      "type": "other",
      "title": "Terror Network Slaughtering Nigerian христиане Has Escaped America’s чёрный список",
      "description": "Experts и policy change-makers tell Daily Caller that правительства are failing confront primary угроза для христиане в Nigeria.",
      "source": "newsapi:The Daily Caller",
      "url": "https://dailycaller.com/2026/07/07/fulani-ethnic-militia-isis-nigeria-boko-haram-christians-donald-trump-riley-moore-chris-smith/",
      "victims": 0
    },
    {
      "date": "2026-07-03",
      "lat": 21.0737,
      "lng": 85.2762,
      "country": "India",
      "city": "Odisha",
      "type": "murder",
      "title": "If Stan Swamy, Martyr, Were Alive сегодня…",
      "description": "Exactly five годы ago, на 5 июль 2021, Jesuit Father Stan Swamy was убит. He was убит because he отказано kow-tow brutal, post If Stan Swamy, Martyr, Were Alive сегодня… appeared первый на Indian Catholic Matters.",
      "source": "newsapi:Indiancatholicmatters.org",
      "url": "https://www.indiancatholicmatters.org/if-stan-swamy-the-martyr-were-alive-today/",
      "victims": 0
    },
    {
      "date": "2026-07-01",
      "lat": 24.7407,
      "lng": 66.9424,
      "country": "Pakistan",
      "city": "Karachi",
      "type": "murder",
      "title": "Христианин Accused богохульство Dies в тюрьма в Pakistan",
      "description": "LAHORE, Pakistan (христианин Daily International–утро Star News) – 61-год-old Catholic в Pakistan страдания из advanced dementia погиб на среда (июль 1) после nearly год в тюрьма awaiting суд на false богохульство обвинение, sources said.",
      "source": "morningstarnews",
      "url": "https://morningstarnews.org/2026/07/christian-accused-of-blasphemy-dies-in-jail-in-pakistan/",
      "victims": 0
    },
    {
      "date": "2026-07-05",
      "lat": 31.2996,
      "lng": 121.6042,
      "country": "China",
      "city": "Shanghai",
      "type": "arrest",
      "title": "China Releases пастор Two месяцы после президент Trump Advocated для His Release с Xi Jinping",
      "description": "Президент Donald Trump’s relationship с Chinese leader Xi Jinping paid dividends на этой неделе as заключён подпольная церковь пастор was released two месяцы после президент personally lobbied для his freedom. post China Releases пастор Tw",
      "source": "newsapi:Breitbart News",
      "url": "https://www.breitbart.com/faith/2026/07/05/china-releases-pastor-two-months-after-president-trump-advocated-for-his-release-with-xi/",
      "victims": 0
    },
    {
      "date": "2026-07-03",
      "lat": 33.8359,
      "lng": 71.3565,
      "country": "Pakistan",
      "city": "Peshawar",
      "type": "murder",
      "title": "Catholic accused богохульство dies в Pakistani custody",
      "description": "Amir Peter, younger брат Catholic священник в Lahore, погиб июль 1 пока held на богохульство обвинение, месяцы после doctors declared him mentally unfit stand суд.",
      "source": "catholicNewsAgency",
      "url": "https://www.ewtnnews.com/world/asia-pacific/blasphemy-accused-catholic-dies-in-custody-in-pakistan",
      "victims": 0
    },
    {
      "date": "2026-06-19",
      "lat": 9.3314,
      "lng": 9.3601,
      "country": "Nigeria",
      "city": "Plateau",
      "type": "kidnapping",
      "title": "Appeals для release Nigerian христианин girl still held ИГИЛ после 8 годы",
      "description": "Leah, who was 14 когда she was похищен, could have been released if she renounced her вера but she отказано.",
      "source": "christiantoday",
      "url": "https://www.christiantoday.com/news/appeals-for-release-of-nigerian-christian-girl-still-held-by-isis-after-8-years",
      "victims": 0
    },
    {
      "date": "2026-06-26",
      "lat": 20.9316,
      "lng": 85.1485,
      "country": "India",
      "city": "Odisha",
      "type": "other",
      "title": "Христианские семьи Hospitalized после Severe нападение в India",
      "description": "NEW DELHI (утро Star News) – Nine tribal люди в India have been released на залог после they sent 13 христиане больница с severe ранения, sources said. followers traditional tribal религия were released на залог на июнь 15. Th",
      "source": "morningstarnews",
      "url": "https://morningstarnews.org/2026/06/christian-families-hospitalized-after-severe-assault-in-india/",
      "victims": 13
    },
    {
      "date": "2026-06-16",
      "lat": 28.4886,
      "lng": 76.976,
      "country": "India",
      "city": "Delhi",
      "type": "murder",
      "title": "Пасторы among заложники found погибшие amid tensions between христианин groups в Manipur",
      "description": "Пока number люди unaccounted для в northeastern Indian штат Manipur has fallen из 20 two, с four six bodies recovered identified на этой неделе, retaliatory атаки continue following cycle похищения between Kuki-Zo",
      "source": "christiantoday",
      "url": "https://www.christiantoday.com/news/pastors-among-hostages-found-dead-amid-tensions-between-christian-groups-in-manipur",
      "victims": 0
    },
    {
      "date": "2026-07-01",
      "lat": 12.0705,
      "lng": 13.3186,
      "country": "Nigeria",
      "city": "Borno",
      "type": "kidnapping",
      "title": "Исламский экстремисты Abduct Students в Nigeria",
      "description": "На понедельник утро, боевики атакован правительство день Secondary школа в Lassa, Askira/Uba Local правительство Area Borno штат пока students were sitting для National Examinations совет examinations, abducting students и школа staff и убийство",
      "source": "persecution",
      "url": "https://persecution.org/2026/07/01/islamic-extremists-abduct-students-in-nigeria/",
      "victims": 0
    },
    {
      "date": "2026-06-23",
      "lat": 34.1443,
      "lng": 71.6787,
      "country": "Pakistan",
      "city": "Peshawar",
      "type": "murder",
      "title": "Pakistani суд acquits blind Catholic мужчина в богохульство case",
      "description": "Lahore суд cited insufficient evidence в clearing Nadeem Masih, blind Catholic who spent nearly 10 месяцы в тюрьма на богохульство обвинение carrying mandatory смерть penalty.",
      "source": "newsapi:Ewtnnews.com",
      "url": "https://www.ewtnnews.com/world/asia-pacific/pakistani-court-acquits-blind-catholic-man-in-blasphemy-case",
      "victims": 0
    },
    {
      "date": "2026-06-20",
      "lat": 11.902,
      "lng": 8.426,
      "country": "Nigeria",
      "city": "Kano",
      "type": "other",
      "title": "Nigerian activists rally для преследуемый христиане near White House",
      "description": "Save Nigeria Rally included speakers such as Alveda король, PhD, niece civil rights activist Martin Luther король Jr., along с представители из all six geopolitical zones Nigeria.",
      "source": "newsapi:Ewtnnews.com",
      "url": "https://www.ewtnnews.com/world/us/nigerian-activists-rally-for-persecuted-christians-near-white-house",
      "victims": 0
    },
    {
      "date": "2026-06-11",
      "lat": 8.9877,
      "lng": 9.3421,
      "country": "Nigeria",
      "city": "Plateau",
      "type": "murder",
      "title": "Four приговорён смерть terror атака на Nigerian церковь",
      "description": "40 люди погиб в атака во время Pentecost воскресенье service в 2022.",
      "source": "christiantoday",
      "url": "https://www.christiantoday.com/news/four-sentenced-to-death-over-terror-attack-on-nigerian-church",
      "victims": 40
    },
    {
      "date": "2026-07-08",
      "lat": 23.5167,
      "lng": 113.7147,
      "country": "China",
      "city": "Guangdong",
      "type": "other",
      "title": "Chinese пастор released US as goodwill gesture на 4 июль",
      "description": "Zion церковь is one largest незарегистрированные церкви в China.",
      "source": "christiantoday",
      "url": "https://www.christiantoday.com/news/chinese-pastor-released-to-us-as-goodwill-gesture-on-4-july",
      "victims": 0
    },
    {
      "date": "2026-07-06",
      "lat": 44.029,
      "lng": 87.774,
      "country": "China",
      "city": "Xinjiang",
      "type": "arrest",
      "title": "China releases задержан христианин пастор Ezra Jin Mingri",
      "description": "Jin was арестован Chinese власти на Oct. 10, 2025.",
      "source": "catholicNewsAgency",
      "url": "https://www.ewtnnews.com/world/us/china-releases-pastor-ezra-jin-mingri",
      "victims": 0
    },
    {
      "date": "2026-07-06",
      "lat": 4.4285,
      "lng": 18.7394,
      "country": "Central African Republic",
      "city": "Bangui",
      "type": "arrest",
      "title": "Христианин братья defend housing осуждён sex abusers amid insolvency claims в Australia",
      "description": "Христианин братья have defended their decision retain nine осуждён ребёнок sex offenders within their религиозный order, saying they have \"Gospel imperative\" continue caring для all members, according суд documents filed в Australia.",
      "source": "christiantoday",
      "url": "https://www.christiantoday.com/news/christian-brothers-defend-housing-convicted-sex-abusers-amid-insolvency-claims-in-australia",
      "victims": 0
    },
    {
      "date": "2026-07-05",
      "lat": 43.5742,
      "lng": 87.8023,
      "country": "China",
      "city": "Xinjiang",
      "type": "other",
      "title": "China releases подпольная церковь пастор после месяцы в задержание",
      "description": "Ezra Jin’s семья says Zion церковь founder arrived в US после месяцы в задержание в China.",
      "source": "newsapi:Al Jazeera English",
      "url": "https://www.aljazeera.com/news/2026/7/5/china-releases-underground-church-pastor-after-months-in-detention",
      "victims": 0
    },
    {
      "date": "2026-07-03",
      "lat": -6.2474,
      "lng": 106.9862,
      "country": "Indonesia",
      "city": "Jakarta",
      "type": "discrimination",
      "title": "Мусульмане Protest Presence церковь в Indonesia",
      "description": "SURABAYA, Indonesia (утро Star News) – исламисты в июнь demonstrated against presence церковь в one город в West Java провинция, Indonesia и prevented funeral месса в another, local sources reported. Dozens мусульмане demonstrated aga",
      "source": "morningstarnews",
      "url": "https://morningstarnews.org/2026/07/muslims-protest-presence-of-church-in-indonesia/",
      "victims": 24
    },
    {
      "date": "2026-06-16",
      "lat": 29.4253,
      "lng": 52.7988,
      "country": "Iran",
      "city": "Shiraz",
      "type": "other",
      "title": "New AI tool makes it easier для Iranians access Gospel",
      "description": "Министерство seeking bring христианство люди Iran has developed AI tool answer common questions о вера.",
      "source": "christiantoday",
      "url": "https://www.christiantoday.com/news/new-ai-tool-makes-it-easier-for-iranians-to-access-the-gospel",
      "victims": 0
    },
    {
      "date": "2026-07-05",
      "lat": 4.2154,
      "lng": 18.656,
      "country": "Central African Republic",
      "city": "Bangui",
      "type": "other",
      "title": "Leo remembers Vietnamese Blessed, martyr после WWII",
      "description": "После молящийся midday Angelus, папа Leo recalled testimony и beatification Vietnamese священник François-Xavier Truong Buu Diep (1897–1946). He was beatified во время месса celebrated кардинал Luis Antonio Tagle Tac Say святыня на Ju",
      "source": "aleteia",
      "url": "https://aleteia.org/2026/07/05/leo-remembers-vietnamese-blessed-martyr-after-wwii/",
      "victims": 0
    },
    {
      "date": "2026-07-04",
      "lat": 10.4583,
      "lng": -66.7545,
      "country": "Venezuela",
      "city": "Caracas",
      "type": "other",
      "title": "Церковь в Venezuela 'overwhelmed' после после devastating earthquakes",
      "description": "На прошлой неделе's earthquakes have only added испытания already faced oppressed христиане в Venezuela с some reporting disparities в access humanitarian assistance.",
      "source": "christiantoday",
      "url": "https://www.christiantoday.com/news/christians-in-venezuela-face-mounting-challenges-after-devastating-earthquakes",
      "victims": 0
    },
    {
      "date": "2026-07-03",
      "lat": 15.5116,
      "lng": 32.7722,
      "country": "Sudan",
      "city": "Khartoum",
      "type": "murder",
      "title": "Teenage Girl Faces смерть для Following Jesus",
      "description": "Since she decided follow Jesus в июнь 2025, 15-год-old Indii Mikaa’el has lost her education и comfort her home. She could also lose her life. Born в мусульманин семья в Haroji Wado, near Ethiopia’s border с Sudan, Mikaa’el сейчас li",
      "source": "persecution",
      "url": "https://persecution.org/2026/07/03/teenage-girl-faces-death-for-following-jesus/",
      "victims": 0
    },
    {
      "date": "2026-06-30",
      "lat": 21.1519,
      "lng": 81.7301,
      "country": "India",
      "city": "Chhattisgarh",
      "type": "other",
      "title": "Going Distance Help Those в Need",
      "description": "Two годы после Manish left индуизм follow Jesus в 2008, he began sharing gospel full-time в local индус communities в India. недавно, индус nationalists have started push back. на Feb. 22, as пастор Manish led воскресенье богослужение service",
      "source": "persecution",
      "url": "https://persecution.org/2026/06/30/going-the-distance-to-help-those-in-need/",
      "victims": 0
    },
    {
      "date": "2026-06-12",
      "lat": 28.5526,
      "lng": 77.3271,
      "country": "India",
      "city": "Delhi",
      "type": "other",
      "title": "Systemic anti-христианин violence laid bare public hearing в India",
      "description": "Епископы, кардиналы и архиепископы were accused not standing с ordinary христиане страдания violence в their communities.",
      "source": "christiantoday",
      "url": "https://www.christiantoday.com/news/systemic-anti-christian-violence-laid-bare-at-public-hearing-in-india",
      "victims": 0
    },
    {
      "date": "2026-07-08",
      "lat": 35.9884,
      "lng": 43.8625,
      "country": "Iraq",
      "city": "Erbil",
      "type": "other",
      "title": "Папа Leo XIV Iraqi христиане: Be Christ’s light в challenging times",
      "description": "Vatican published video message из pontiff на июль 8 для Ankawa молодёжь Meeting.",
      "source": "catholicNewsAgency",
      "url": "https://www.ewtnnews.com/vatican/pope-leo-xiv-to-iraqi-christians-be-christ-s-light-in-challenging-times",
      "victims": 0
    },
    {
      "date": "2026-07-07",
      "lat": 43.5675,
      "lng": 87.3876,
      "country": "China",
      "city": "Xinjiang",
      "type": "other",
      "title": "‘Miracle’: China releases христианин пастор following Trump’s appeal",
      "description": "Reunited с his семья праздник выходные",
      "source": "newsapi:Wnd.com",
      "url": "https://www.wnd.com/2026/07/miracle-china-releases-christian-pastor-following-trumps-appeal/",
      "victims": 0
    },
    {
      "date": "2026-07-06",
      "lat": 19.6207,
      "lng": -99.3019,
      "country": "Mexico",
      "city": "Mexico City",
      "type": "other",
      "title": "YWAM mobilizes церкви в multi-country outreach as World Cup knockout stage continues",
      "description": "International миссионер movement молодёжь с Mission (YWAM) is running coordinated outreach кампания across Canada, Mexico, и United штаты as 2026 FIFA World Cup advances through its intense knockout stages.",
      "source": "christiantoday",
      "url": "https://www.christiantoday.com/news/ywam-mobilizes-churches-in-multi-country-outreach-as-world-cup-knockout-stage-continues",
      "victims": 0
    },
    {
      "date": "2026-07-01",
      "lat": 10.2513,
      "lng": -66.9127,
      "country": "Venezuela",
      "city": "Caracas",
      "type": "murder",
      "title": "Some семьи have had remove their own погибшие из rubble в Venezuela, says церковь leader",
      "description": "Церковь sources в country fear as many as 250,000 люди май have been left homeless.",
      "source": "christiantoday",
      "url": "https://www.christiantoday.com/news/some-families-have-had-to-remove-their-own-dead-from-rubble-in-venezuela-says-church-leader",
      "victims": 0
    },
    {
      "date": "2026-06-23",
      "lat": 4.9481,
      "lng": -73.9571,
      "country": "Colombia",
      "city": "Bogota",
      "type": "attack",
      "title": "Церковь leaders угрожали боевики в run-up Colombian presidential election, says rights group",
      "description": "CSW is urging new Colombian президент reinstate special protection measures для религиозный leaders",
      "source": "christiantoday",
      "url": "https://www.christiantoday.com/news/church-leaders-threatened-by-militants-in-run-up-to-colombian-presidential-election-says-rights-group",
      "victims": 0
    }
  ]
}